markon.py
markon-1.0.0.dist-info/LICENSE
markon-1.0.0.dist-info/METADATA
markon-1.0.0.dist-info/WHEEL
markon-1.0.0.dist-info/top_level.txt
markon-1.0.0.dist-info/RECORD
