Metadata-Version: 2.1
Name: markon
Version: 1.0.0
Summary: Simple CTMC solver for Python
Home-page: http://gitlab.com/fredrikh/markon
Author: Fredrik Bakkevig Haugli
Author-email: fredrik.haugli@gmail.com
License: MIT
Project-URL: Bug Reports, https://gitlab.com/fredrikh/markon/-/issues
Project-URL: Source, https://gitlab.com/fredrikh/markon/
Platform: UNKNOWN
Classifier: License :: OSI Approved :: MIT License
Classifier: Programming Language :: Python :: 3
License-File: LICENSE
Requires-Dist: sympy
